test_runner_cdns/__init__.py
test_runner_cdns/ecn_runner.py
test_runner_cdns/rtl_runner.py
test_runner_cdns-0.1.dist-info/METADATA
test_runner_cdns-0.1.dist-info/WHEEL
test_runner_cdns-0.1.dist-info/top_level.txt
test_runner_cdns-0.1.dist-info/RECORD
