Metadata-Version: 2.4
Name: test_runner_cdns
Version: 0.1
Summary: Reusable runners for ECN and RTL analysis using user-supplied rtl_analysis.py
Author: Your Name
Requires-Python: >=3.7
Dynamic: author
Dynamic: requires-python
Dynamic: summary
